{
    "SendMessageFunction": {
        "AWS_REGION": "local",
        "DYNAMO_END_POINT": "http://dynamodb-local:8000",
        "TABLE_NAME": "simplechat_connections"
    },
    "OnConnectFunction": {
        "AWS_REGION": "local",
        "DYNAMO_END_POINT": "http://dynamodb-local:8000",
        "TABLE_NAME": "simplechat_connections"
    },
    "OnDisconnectFunction": {
        "AWS_REGION": "local",
        "DYNAMO_END_POINT": "http://dynamodb-local:8000",
        "TABLE_NAME": "simplechat_connections"
    }
}